MANIFEST.in
setup.py
cache_panel/__init__.py
cache_panel/panel.py
cache_panel/templates/.DS_Store
cache_panel/templates/cache_panel/.DS_Store
cache_panel/templates/cache_panel/cache.html
django_cache_panel.egg-info/PKG-INFO
django_cache_panel.egg-info/SOURCES.txt
django_cache_panel.egg-info/dependency_links.txt
django_cache_panel.egg-info/not-zip-safe
django_cache_panel.egg-info/top_level.txt