Metadata-Version: 1.1
Name: django-cache-panel
Version: 0.1
Summary: A more detailed cache panel for the Django Debug Toolbar
Home-page: http://github.com/lincolnloop/django-cache-panel
Author: Brandon Konkle
Author-email: brandon@lincolnloop.com
License: UNKNOWN
Platform: UNKNOWN
Requires: Django
Requires: debug_toolbar
Provides: cache_panel
